Workbook

Sheet 📋 INDEX & TIPS
A1: 🐱 Meo's Vietnamese B2 Word List — COMPLETE SERIES (All 5 Parts)
A2: =CONCATENATE("Southern Vietnamese (Saigon) | For Cantonese Speakers | ",TEXT(B10,"#,##0")," words — Series Complete 🎯") -> Southern Vietnamese (Saigon) | For Cantonese Speakers | 156 words — Series Complete 🎯
A4: SERIES OVERVIEW
A5: Part | B5: Words | D5: Coverage
A6: Part 1 — Foundations | B6: =COUNTIF('📚 All Words (Combined)'!$B:$B,"Part 1 — Foundations") -> 659 | D6: Pronouns, Numbers, Time, Core Verbs, Adjectives, Food, Places, Body & more
A7: Part 2 — Intermediate | B7: =COUNTIF('📚 All Words (Combined)'!$B:$B,"Part 2 — Intermediate") -> 524 | D7: Business, Legal, Tech, Health, Culture, Abstract Concepts, Grammar & Particles
A8: Part 3 — Advanced | B8: =COUNTIF('📚 All Words (Combined)'!$B:$B,"Part 3 — Advanced") -> 339 | D8: Idioms, Formal Writing, Spoken Southern, Economics, Arts, Discourse Markers
A9: Part 4 — Completion | B9: =COUNTIF('📚 All Words (Combined)'!$B:$B,"Part 4 — Completion") -> 284 | D9: Personality, Cause/Effect, Academic, Emotions, Animals, High Frequency Fill
A10: Part 5 — Final | B10: =COUNTIF('📚 All Words (Combined)'!$B:$B,"Part 5 — Final") -> 156 | D10: Work, Shopping, Apps, Tones, Grammar Structures, Essential Fill
A11: 🏆 GRAND TOTAL — Complete Series | B11: =SUM(B6,B7,B8,B9,B10) -> 1962 | D11: 🎯 Series complete! Target: 2,000 words for B2 by June 2026
A14: 📅 STUDY PACE GUIDE — B2 BY JUNE 2026
A15: Period | C15: Focus | D15: Method
A16: Feb–Mar 2026 | C16: Part 1 (659 words) | D16: ~15 words/day — Foundation sprint
A17: Mar–Apr 2026 | C17: Part 2 (524 words) | D17: ~12 words/day — Build intermediate vocab
A18: Apr–May 2026 | C18: Parts 3+4 (623 words) | D18: ~10 words/day — Advanced push
A19: May–Jun 2026 | C19: Part 5 + Review | D19: Anki SRS + shadowing + conversation practice
A20: Jun 2026 | C20: B2 Test | D20: You've got this! Sino-Viet advantage is huge 💪
A23: PART 1 — FOUNDATIONS
A24: Southern Vietnamese (Saigon) | Cantonese tones | Sino-Vietnamese connections highlighted
A25: Category | B25: Words | D25: Key Learning Tip
A26: Pronouns & People | B26: =COUNTIFS('📚 All Words (Combined)'!$B:$B,"Part 1 — Foundations",'📚 All Words (Combined)'!$G:$G,"Pronouns & People") -> 27 | D26: Master pronouns first — they reflect social relationships and change constantly
A27: Numbers | B27: =COUNTIFS('📚 All Words (Combined)'!$B:$B,"Part 1 — Foundations",'📚 All Words (Combined)'!$G:$G,"Numbers") -> 20 | D27: Sino-Viet numbers map closely to Cantonese: mot=jat, hai=ji, ba=saam...
A28: Time | B28: =COUNTIFS('📚 All Words (Combined)'!$B:$B,"Part 1 — Foundations",'📚 All Words (Combined)'!$G:$G,"Time") -> 36 | D28: No verb conjugation! Use da(past)/dang(now)/se(future) particles instead
A29: Greetings | B29: =COUNTIFS('📚 All Words (Combined)'!$B:$B,"Part 1 — Foundations",'📚 All Words (Combined)'!$G:$G,"Greetings") -> 14 | D29: Essential daily phrases — 'da' is Southern polite 'yes', not Northern 'vang'
A30: Core Verbs | B30: =COUNTIFS('📚 All Words (Combined)'!$B:$B,"Part 1 — Foundations",'📚 All Words (Combined)'!$G:$G,"Core Verbs") -> 76 | D30: Backbone vocabulary — learn these 80 verbs before anything else
A31: Adjectives | B31: =COUNTIFS('📚 All Words (Combined)'!$B:$B,"Part 1 — Foundations",'📚 All Words (Combined)'!$G:$G,"Adjectives") -> 57 | D31: Adjectives come AFTER the noun (opposite of English but like some Chinese patterns)
A32: Question Words | B32: =COUNTIFS('📚 All Words (Combined)'!$B:$B,"Part 1 — Foundations",'📚 All Words (Combined)'!$G:$G,"Question Words") -> 11 | D32: Learn these 11 words and you can ask almost any question
A33: Prepositions | B33: =COUNTIFS('📚 All Words (Combined)'!$B:$B,"Part 1 — Foundations",'📚 All Words (Combined)'!$G:$G,"Prepositions") -> 16 | D33: Spatial and relational words — critical for giving/following directions
A34: Connectors | B34: =COUNTIFS('📚 All Words (Combined)'!$B:$B,"Part 1 — Foundations",'📚 All Words (Combined)'!$G:$G,"Connectors") -> 15 | D34: Build complex sentences — ~80% of these are Sino-Vietnamese!
A35: Food & Drink | B35: =COUNTIFS('📚 All Words (Combined)'!$B:$B,"Part 1 — Foundations",'📚 All Words (Combined)'!$G:$G,"Food & Drink") -> 37 | D35: Crucial for daily survival — huge regional variation (heo vs lon, ly vs coc)
A36: Transport | B36: =COUNTIFS('📚 All Words (Combined)'!$B:$B,"Part 1 — Foundations",'📚 All Words (Combined)'!$G:$G,"Transport") -> 23 | D36: Essential for HCMC — xe may (motorbike) culture is everywhere
A37: Places | B37: =COUNTIFS('📚 All Words (Combined)'!$B:$B,"Part 1 — Foundations",'📚 All Words (Combined)'!$G:$G,"Places") -> 36 | D37: Combines with verbs of movement — di/den/ve create powerful phrases
A38: Body & Health | B38: =COUNTIFS('📚 All Words (Combined)'!$B:$B,"Part 1 — Foundations",'📚 All Words (Combined)'!$G:$G,"Body & Health") -> 29 | D38: Most medical terms are Sino-Viet — huge advantage for you!
A39: Shopping & Money | B39: =COUNTIFS('📚 All Words (Combined)'!$B:$B,"Part 1 — Foundations",'📚 All Words (Combined)'!$G:$G,"Shopping & Money") -> 20 | D39: Bargaining is cultural — master price words immediately
A40: Work & Education | B40: =COUNTIFS('📚 All Words (Combined)'!$B:$B,"Part 1 — Foundations",'📚 All Words (Combined)'!$G:$G,"Work & Education") -> 25 | D40: Nearly all professional terms are Sino-Vietnamese
A41: Technology | B41: =COUNTIFS('📚 All Words (Combined)'!$B:$B,"Part 1 — Foundations",'📚 All Words (Combined)'!$G:$G,"Technology") -> 17 | D41: Mix of Sino-Viet and loanwords from English/French
A42: Nature | B42: =COUNTIFS('📚 All Words (Combined)'!$B:$B,"Part 1 — Foundations",'📚 All Words (Combined)'!$G:$G,"Nature") -> 25 | D42: Weather vocab important — tropical climate means rain/heat talk is constant
A43: Feelings | B43: =COUNTIFS('📚 All Words (Combined)'!$B:$B,"Part 1 — Foundations",'📚 All Words (Combined)'!$G:$G,"Feelings") -> 13 | D43: Emotional vocabulary for deeper, more natural conversation
A44: Social & Cultural | B44: =COUNTIFS('📚 All Words (Combined)'!$B:$B,"Part 1 — Foundations",'📚 All Words (Combined)'!$G:$G,"Social & Cultural") -> 20 | D44: Essential for cultural understanding and context
A45: Adverbs | B45: =COUNTIFS('📚 All Words (Combined)'!$B:$B,"Part 1 — Foundations",'📚 All Words (Combined)'!$G:$G,"Adverbs") -> 24 | D45: Rat (very) and qua (too much) are used constantly — learn these early!
A46: Clothes | B46: =COUNTIFS('📚 All Words (Combined)'!$B:$B,"Part 1 — Foundations",'📚 All Words (Combined)'!$G:$G,"Clothes") -> 14 | D46: Shopping vocabulary — useful for markets and malls in Saigon
A47: Communication | B47: =COUNTIFS('📚 All Words (Combined)'!$B:$B,"Part 1 — Foundations",'📚 All Words (Combined)'!$G:$G,"Communication") -> 13 | D47: Meta-language for talking about learning Vietnamese itself
A48: Household | B48: =COUNTIFS('📚 All Words (Combined)'!$B:$B,"Part 1 — Foundations",'📚 All Words (Combined)'!$G:$G,"Household") -> 15 | D48: For home life and giving/following everyday instructions
A49: Abstract Concepts | B49: =COUNTIFS('📚 All Words (Combined)'!$B:$B,"Part 1 — Foundations",'📚 All Words (Combined)'!$G:$G,"Abstract Concepts") -> 32 | D49: ~90% Sino-Vietnamese — leverage your Chinese massively here!
A50: Classifiers | B50: =COUNTIFS('📚 All Words (Combined)'!$B:$B,"Part 1 — Foundations",'📚 All Words (Combined)'!$G:$G,"Classifiers") -> 11 | D50: Critical feature shared with Cantonese — cai, con, chiec, cuon etc.
A51: Weather | B51: =COUNTIFS('📚 All Words (Combined)'!$B:$B,"Part 1 — Foundations",'📚 All Words (Combined)'!$G:$G,"Weather") -> 7 | D51: Tropical seasons: rainy season (mua mua) May-Nov, dry season Dec-Apr
A52: Directions | B52: =COUNTIFS('📚 All Words (Combined)'!$B:$B,"Part 1 — Foundations",'📚 All Words (Combined)'!$G:$G,"Directions") -> 11 | D52: Essential for navigating Vietnamese cities — combine with transport words
A53: Common Phrases | B53: =COUNTIFS('📚 All Words (Combined)'!$B:$B,"Part 1 — Foundations",'📚 All Words (Combined)'!$G:$G,"Common Phrases") -> 15 | D53: Ready-to-use sentences for immediate real-world communication
A54: Total — Part 1 — Foundations | B54: =COUNTIF('📚 All Words (Combined)'!$B:$B,"Part 1 — Foundations") -> 659
A56: PART 2 — INTERMEDIATE
A57: Advanced vocabulary: Business, Legal, Culture, Grammar, Science & more | Use with Part 1
A58: Category | B58: Words | D58: Priority for B2
A59: Business & Finance | B59: =COUNTIFS('📚 All Words (Combined)'!$B:$B,"Part 2 — Intermediate",'📚 All Words (Combined)'!$G:$G,"Business & Finance") -> 40 | D59: HIGH — If working in Vietnam, master these immediately
A60: Legal & Government | B60: =COUNTIFS('📚 All Words (Combined)'!$B:$B,"Part 2 — Intermediate",'📚 All Words (Combined)'!$G:$G,"Legal & Government") -> 21 | D60: MEDIUM — Important for expat life, admin, visas
A61: Education Advanced | B61: =COUNTIFS('📚 All Words (Combined)'!$B:$B,"Part 2 — Intermediate",'📚 All Words (Combined)'!$G:$G,"Education Advanced") -> 23 | D61: MEDIUM — Useful for academic/professional contexts
A62: Health & Medical | B62: =COUNTIFS('📚 All Words (Combined)'!$B:$B,"Part 2 — Intermediate",'📚 All Words (Combined)'!$G:$G,"Health & Medical") -> 25 | D62: HIGH — Essential, especially Sino-Viet medical terms
A63: Food Advanced | B63: =COUNTIFS('📚 All Words (Combined)'!$B:$B,"Part 2 — Intermediate",'📚 All Words (Combined)'!$G:$G,"Food Advanced") -> 30 | D63: HIGH — Deepen food vocab; cooking methods + Southern dishes
A64: Housing | B64: =COUNTIFS('📚 All Words (Combined)'!$B:$B,"Part 2 — Intermediate",'📚 All Words (Combined)'!$G:$G,"Housing") -> 21 | D64: HIGH — Essential for renting in HCMC
A65: Environment | B65: =COUNTIFS('📚 All Words (Combined)'!$B:$B,"Part 2 — Intermediate",'📚 All Words (Combined)'!$G:$G,"Environment") -> 14 | D65: MEDIUM — Common in news/discussion topics
A66: Sports & Leisure | B66: =COUNTIFS('📚 All Words (Combined)'!$B:$B,"Part 2 — Intermediate",'📚 All Words (Combined)'!$G:$G,"Sports & Leisure") -> 24 | D66: MEDIUM — For social conversation and hobbies
A67: Travel & Tourism | B67: =COUNTIFS('📚 All Words (Combined)'!$B:$B,"Part 2 — Intermediate",'📚 All Words (Combined)'!$G:$G,"Travel & Tourism") -> 20 | D67: HIGH — For navigating Vietnam as a visitor/resident
A68: Relationships | B68: =COUNTIFS('📚 All Words (Combined)'!$B:$B,"Part 2 — Intermediate",'📚 All Words (Combined)'!$G:$G,"Relationships") -> 24 | D68: HIGH — For deeper social/family conversations
A69: Media & Entertainment | B69: =COUNTIFS('📚 All Words (Combined)'!$B:$B,"Part 2 — Intermediate",'📚 All Words (Combined)'!$G:$G,"Media & Entertainment") -> 23 | D69: MEDIUM — For following Vietnamese media
A70: Technology Advanced | B70: =COUNTIFS('📚 All Words (Combined)'!$B:$B,"Part 2 — Intermediate",'📚 All Words (Combined)'!$G:$G,"Technology Advanced") -> 22 | D70: MEDIUM-HIGH — Tech industry in Vietnam is booming
A71: Science | B71: =COUNTIFS('📚 All Words (Combined)'!$B:$B,"Part 2 — Intermediate",'📚 All Words (Combined)'!$G:$G,"Science") -> 20 | D71: LOW-MEDIUM — Most are Sino-Viet, good for reading
A72: Abstract Advanced | B72: =COUNTIFS('📚 All Words (Combined)'!$B:$B,"Part 2 — Intermediate",'📚 All Words (Combined)'!$G:$G,"Abstract Advanced") -> 27 | D72: HIGH for B2 — ~90% Sino-Viet, huge advantage!
A73: Expressions | B73: =COUNTIFS('📚 All Words (Combined)'!$B:$B,"Part 2 — Intermediate",'📚 All Words (Combined)'!$G:$G,"Expressions") -> 20 | D73: HIGH — These move you from B1 to B2 level speech
A74: Vietnamese Culture | B74: =COUNTIFS('📚 All Words (Combined)'!$B:$B,"Part 2 — Intermediate",'📚 All Words (Combined)'!$G:$G,"Vietnamese Culture") -> 20 | D74: HIGH — Essential for integration and cultural fluency
A75: More Verbs | B75: =COUNTIFS('📚 All Words (Combined)'!$B:$B,"Part 2 — Intermediate",'📚 All Words (Combined)'!$G:$G,"More Verbs") -> 49 | D75: HIGH — Expand verb repertoire for nuanced communication
A76: More Adjectives | B76: =COUNTIFS('📚 All Words (Combined)'!$B:$B,"Part 2 — Intermediate",'📚 All Words (Combined)'!$G:$G,"More Adjectives") -> 34 | D76: HIGH — Character descriptions, business/professional talk
A77: More Nouns | B77: =COUNTIFS('📚 All Words (Combined)'!$B:$B,"Part 2 — Intermediate",'📚 All Words (Combined)'!$G:$G,"More Nouns") -> 35 | D77: HIGH — Academic and professional vocabulary
A78: Grammar & Particles | B78: =COUNTIFS('📚 All Words (Combined)'!$B:$B,"Part 2 — Intermediate",'📚 All Words (Combined)'!$G:$G,"Grammar & Particles") -> 32 | D78: CRITICAL — Master these for natural-sounding Vietnamese
A79: Total — Part 2 — Intermediate | B79: =COUNTIF('📚 All Words (Combined)'!$B:$B,"Part 2 — Intermediate") -> 524
A81: PART 3 — ADVANCED
A82: Idioms | Formal/Spoken | Culture | Economics | Discourse Markers | Grammar | Arts
A83: Category | B83: Words | D83: Notes
A84: Idioms & Proverbs | B84: =COUNTIFS('📚 All Words (Combined)'!$B:$B,"Part 3 — Advanced",'📚 All Words (Combined)'!$G:$G,"Idioms & Proverbs") -> 16 | D84: HIGH — Learn 10-15 key ones to sound native; many match Chinese proverbs
A85: Formal Writing | B85: =COUNTIFS('📚 All Words (Combined)'!$B:$B,"Part 3 — Advanced",'📚 All Words (Combined)'!$G:$G,"Formal Writing") -> 17 | D85: HIGH for B2 — Official letters, reports, academic writing
A86: Spoken Southern | B86: =COUNTIFS('📚 All Words (Combined)'!$B:$B,"Part 3 — Advanced",'📚 All Words (Combined)'!$G:$G,"Spoken Southern") -> 20 | D86: CRITICAL — Real Saigon daily speech; hổng/vô/dzui etc.
A87: Opinion & Debate | B87: =COUNTIFS('📚 All Words (Combined)'!$B:$B,"Part 3 — Advanced",'📚 All Words (Combined)'!$G:$G,"Opinion & Debate") -> 20 | D87: HIGH for B2 — Argue, explain, present ideas with nuance
A88: Numbers & Math | B88: =COUNTIFS('📚 All Words (Combined)'!$B:$B,"Part 3 — Advanced",'📚 All Words (Combined)'!$G:$G,"Numbers & Math") -> 23 | D88: MEDIUM — Operations and shapes; mostly Sino-Viet
A89: Measurements | B89: =COUNTIFS('📚 All Words (Combined)'!$B:$B,"Part 3 — Advanced",'📚 All Words (Combined)'!$G:$G,"Measurements") -> 14 | D89: MEDIUM — For shopping, cooking, directions
A90: Calendar & Dates | B90: =COUNTIFS('📚 All Words (Combined)'!$B:$B,"Part 3 — Advanced",'📚 All Words (Combined)'!$G:$G,"Calendar & Dates") -> 19 | D90: HIGH — Dates, quarters, lunar calendar essential in Vietnam
A91: Vietnam Geography | B91: =COUNTIFS('📚 All Words (Combined)'!$B:$B,"Part 3 — Advanced",'📚 All Words (Combined)'!$G:$G,"Vietnam Geography") -> 16 | D91: MEDIUM-HIGH — Know your regions, rivers, climate zones
A92: Politics & Society | B92: =COUNTIFS('📚 All Words (Combined)'!$B:$B,"Part 3 — Advanced",'📚 All Words (Combined)'!$G:$G,"Politics & Society") -> 20 | D92: MEDIUM — Understand news and current events
A93: Economics | B93: =COUNTIFS('📚 All Words (Combined)'!$B:$B,"Part 3 — Advanced",'📚 All Words (Combined)'!$G:$G,"Economics") -> 16 | D93: HIGH if working in VN — GDP, inflation, supply chain etc.
A94: Urban Life HCMC | B94: =COUNTIFS('📚 All Words (Combined)'!$B:$B,"Part 3 — Advanced",'📚 All Words (Combined)'!$G:$G,"Urban Life HCMC") -> 20 | D94: CRITICAL if living in HCMC — hẻm, xe ôm, nhậu, shipper...
A95: Digital & Slang | B95: =COUNTIFS('📚 All Words (Combined)'!$B:$B,"Part 3 — Advanced",'📚 All Words (Combined)'!$G:$G,"Digital & Slang") -> 18 | D95: HIGH for social/Gen Z — viral, check-in, flex, TikTok
A96: Food Culture Southern | B96: =COUNTIFS('📚 All Words (Combined)'!$B:$B,"Part 3 — Advanced",'📚 All Words (Combined)'!$G:$G,"Food Culture Southern") -> 20 | D96: HIGH — Deepen your food ordering and dining vocabulary
A97: Politeness & Etiquette | B97: =COUNTIFS('📚 All Words (Combined)'!$B:$B,"Part 3 — Advanced",'📚 All Words (Combined)'!$G:$G,"Politeness & Etiquette") -> 15 | D97: HIGH — Face culture is key; how you speak matters a lot
A98: Health & Wellness | B98: =COUNTIFS('📚 All Words (Combined)'!$B:$B,"Part 3 — Advanced",'📚 All Words (Combined)'!$G:$G,"Health & Wellness") -> 15 | D98: MEDIUM — Everyday health and wellness discussions
A99: Arts & Literature | B99: =COUNTIFS('📚 All Words (Combined)'!$B:$B,"Part 3 — Advanced",'📚 All Words (Combined)'!$G:$G,"Arts & Literature") -> 20 | D99: MEDIUM — For reading news, culture articles, discussions
A100: Discourse Markers | B100: =COUNTIFS('📚 All Words (Combined)'!$B:$B,"Part 3 — Advanced",'📚 All Words (Combined)'!$G:$G,"Discourse Markers") -> 20 | D100: CRITICAL for B2 — These structure your speech and writing
A101: Conditional | B101: =COUNTIFS('📚 All Words (Combined)'!$B:$B,"Part 3 — Advanced",'📚 All Words (Combined)'!$G:$G,"Conditional") -> 10 | D101: HIGH — If/then, unless, provided that — essential grammar
A102: Verb Phrases | B102: =COUNTIFS('📚 All Words (Combined)'!$B:$B,"Part 3 — Advanced",'📚 All Words (Combined)'!$G:$G,"Verb Phrases") -> 20 | D102: HIGH — Common verb+noun combos used constantly in professional contexts
A103: Total — Part 3 — Advanced | B103: =COUNTIF('📚 All Words (Combined)'!$B:$B,"Part 3 — Advanced") -> 339
A105: PART 4 — COMPLETION
A106: Personality | Cause & Effect | Academic | Emotions | Animals | High Frequency Fill
A107: Category | B107: Words | D107: Study Priority
A108: Personality & Character | B108: =COUNTIFS('📚 All Words (Combined)'!$B:$B,"Part 4 — Completion",'📚 All Words (Combined)'!$G:$G,"Personality & Character") -> 24 | D108: HIGH — Describe people naturally; most words are daily use
...

Sheet 📚 All Words (Combined)
A1: # | B1: Part | C1: Vietnamese (Southern) | D1: English Meaning | E1: Chinese Characters | F1: Cantonese Pronunciation | G1: Category | H1: Notes / Sino-Viet Connection
A2: 1 | B2: Part 1 — Foundations | C2: tôi | D2: I / me | E2: 我 | F2: ngoh | G2: Pronouns & People
A3: 2 | B3: Part 1 — Foundations | C3: bạn | D3: you (friend/peer) | E3: 你 | F3: nei | G3: Pronouns & People
A4: 3 | B4: Part 1 — Foundations | C4: anh | D4: he / older brother / you (to older male) | E4: 兄 | F4: hing | G4: Pronouns & People
A5: 4 | B5: Part 1 — Foundations | C5: chị | D5: she / older sister / you (to older female) | E5: 姐 | F5: ze | G5: Pronouns & People
A6: 5 | B6: Part 1 — Foundations | C6: em | D6: younger sibling / I (to elder) | E6: 弟/妹 | F6: dai/mui | G6: Pronouns & People
A7: 6 | B7: Part 1 — Foundations | C7: họ | D7: they / them | E7: 他們 | F7: keoi-dei | G7: Pronouns & People
A8: 7 | B8: Part 1 — Foundations | C8: chúng tôi | D8: we (excl. listener) | E8: 我們 | F8: ngo-dei | G8: Pronouns & People
A9: 8 | B9: Part 1 — Foundations | C9: chúng ta | D9: we (incl. listener) | E9: 咱們 | F9: zaan-dei | G9: Pronouns & People
A10: 9 | B10: Part 1 — Foundations | C10: ông | D10: grandfather / Mr. / you (elderly man) | E10: 老爺/先生 | F10: lo-ye/sin-saang | G10: Pronouns & People
A11: 10 | B11: Part 1 — Foundations | C11: bà | D11: grandmother / Mrs. / you (elderly woman) | E11: 婆婆/太太 | F11: po-po/taai-taai | G11: Pronouns & People
A12: 11 | B12: Part 1 — Foundations | C12: cô | D12: aunt / Miss / you (young woman) | E12: 姑 | F12: gu | G12: Pronouns & People
A13: 12 | B13: Part 1 — Foundations | C13: chú | D13: uncle / you (middle-aged man) | E13: 叔 | F13: suk | G13: Pronouns & People
A14: 13 | B14: Part 1 — Foundations | C14: người | D14: person / people | E14: 人 | F14: jan | G14: Pronouns & People | H14: Sino-Viet: nhân
A15: 14 | B15: Part 1 — Foundations | C15: con | D15: child / classifier for animals | E15: 子 | F15: zi | G15: Pronouns & People
A16: 15 | B16: Part 1 — Foundations | C16: cha / bố | D16: father | E16: 父 | F16: fu | G16: Pronouns & People
A17: 16 | B17: Part 1 — Foundations | C17: mẹ / má | D17: mother | E17: 母 | F17: mou | G17: Pronouns & People | H17: má is Southern
A18: 17 | B18: Part 1 — Foundations | C18: con trai | D18: son / boy | E18: 兒子 | F18: ji-zi | G18: Pronouns & People
A19: 18 | B19: Part 1 — Foundations | C19: con gái | D19: daughter / girl | E19: 女兒 | F19: neoi-ji | G19: Pronouns & People
A20: 19 | B20: Part 1 — Foundations | C20: anh trai | D20: older brother | E20: 兄 | F20: hing | G20: Pronouns & People
A21: 20 | B21: Part 1 — Foundations | C21: chị gái | D21: older sister | E21: 姐姐 | F21: ze-ze | G21: Pronouns & People
A22: 21 | B22: Part 1 — Foundations | C22: em trai | D22: younger brother | E22: 弟弟 | F22: dai-dai | G22: Pronouns & People
A23: 22 | B23: Part 1 — Foundations | C23: em gái | D23: younger sister | E23: 妹妹 | F23: mui-mui | G23: Pronouns & People
A24: 23 | B24: Part 1 — Foundations | C24: bạn bè | D24: friends | E24: 朋友 | F24: pang-jau | G24: Pronouns & People
A25: 24 | B25: Part 1 — Foundations | C25: gia đình | D25: family | E25: 家庭 | F25: gaa-ting | G25: Pronouns & People | H25: Sino-Viet: gia đình
A26: 25 | B26: Part 1 — Foundations | C26: vợ | D26: wife | E26: 妻 | F26: chai | G26: Pronouns & People
A27: 26 | B27: Part 1 — Foundations | C27: chồng | D27: husband | E27: 夫 | F27: fu | G27: Pronouns & People
A28: 27 | B28: Part 1 — Foundations | C28: cháu | D28: niece/nephew/grandchild | E28: 侄/孫 | F28: zat/syun | G28: Pronouns & People
A29: 28 | B29: Part 1 — Foundations | C29: không | D29: zero | E29: 零 | F29: ling | G29: Numbers
A30: 29 | B30: Part 1 — Foundations | C30: một | D30: one | E30: 一 | F30: jat | G30: Numbers
A31: 30 | B31: Part 1 — Foundations | C31: hai | D31: two | E31: 二 | F31: ji | G31: Numbers
A32: 31 | B32: Part 1 — Foundations | C32: ba | D32: three | E32: 三 | F32: saam | G32: Numbers
A33: 32 | B33: Part 1 — Foundations | C33: bốn | D33: four | E33: 四 | F33: sei | G33: Numbers
A34: 33 | B34: Part 1 — Foundations | C34: năm | D34: five / year | E34: 五/年 | F34: ng/nin | G34: Numbers | H34: same word means year too
A35: 34 | B35: Part 1 — Foundations | C35: sáu | D35: six | E35: 六 | F35: luk | G35: Numbers
A36: 35 | B36: Part 1 — Foundations | C36: bảy | D36: seven | E36: 七 | F36: cat | G36: Numbers
A37: 36 | B37: Part 1 — Foundations | C37: tám | D37: eight | E37: 八 | F37: baat | G37: Numbers
A38: 37 | B38: Part 1 — Foundations | C38: chín | D38: nine | E38: 九 | F38: gau | G38: Numbers
A39: 38 | B39: Part 1 — Foundations | C39: mười | D39: ten | E39: 十 | F39: sap | G39: Numbers
A40: 39 | B40: Part 1 — Foundations | C40: mười một | D40: eleven | E40: 十一 | F40: sap-jat | G40: Numbers
A41: 40 | B41: Part 1 — Foundations | C41: hai mươi | D41: twenty | E41: 二十 | F41: ji-sap | G41: Numbers
A42: 41 | B42: Part 1 — Foundations | C42: trăm | D42: hundred | E42: 百 | F42: baak | G42: Numbers | H42: Sino-Viet: bách
A43: 42 | B43: Part 1 — Foundations | C43: nghìn / ngàn | D43: thousand | E43: 千 | F43: cin | G43: Numbers | H43: ngàn is Southern
A44: 43 | B44: Part 1 — Foundations | C44: triệu | D44: million | E44: 百萬 | F44: baak-maan | G44: Numbers | H44: Sino-Viet: triệu
A45: 44 | B45: Part 1 — Foundations | C45: tỷ | D45: billion | E45: 十億 | F45: sap-jik | G45: Numbers
A46: 45 | B46: Part 1 — Foundations | C46: nửa | D46: half | E46: 半 | F46: bun | G46: Numbers
A47: 46 | B47: Part 1 — Foundations | C47: đôi | D47: pair/couple | E47: 對 | F47: deoi | G47: Numbers
A48: 47 | B48: Part 1 — Foundations | C48: vài | D48: a few / several | E48: 幾個 | F48: gei-go | G48: Numbers
A49: 48 | B49: Part 1 — Foundations | C49: giờ | D49: hour / o'clock | E49: 小時/點 | F49: siu-si/dim | G49: Time
A50: 49 | B50: Part 1 — Foundations | C50: phút | D50: minute | E50: 分鐘 | F50: fan-zung | G50: Time
A51: 50 | B51: Part 1 — Foundations | C51: giây | D51: second | E51: 秒 | F51: miu | G51: Time
A52: 51 | B52: Part 1 — Foundations | C52: ngày | D52: day | E52: 日 | F52: jat | G52: Time
A53: 52 | B53: Part 1 — Foundations | C53: tuần | D53: week | E53: 星期 | F53: sing-kei | G53: Time
A54: 53 | B54: Part 1 — Foundations | C54: tháng | D54: month | E54: 月 | F54: jyut | G54: Time
A55: 54 | B55: Part 1 — Foundations | C55: năm | D55: year | E55: 年 | F55: nin | G55: Time | H55: same word as five
A56: 55 | B56: Part 1 — Foundations | C56: hôm nay | D56: today | E56: 今天 | F56: gam-tin | G56: Time
A57: 56 | B57: Part 1 — Foundations | C57: hôm qua | D57: yesterday | E57: 昨天 | F57: zok-tin | G57: Time
A58: 57 | B58: Part 1 — Foundations | C58: ngày mai | D58: tomorrow | E58: 明天 | F58: ming-tin | G58: Time
A59: 58 | B59: Part 1 — Foundations | C59: bây giờ | D59: now | E59: 現在 | F59: jin-zoi | G59: Time
A60: 59 | B60: Part 1 — Foundations | C60: sau | D60: after / later | E60: 後 | F60: hau | G60: Time
A61: 60 | B61: Part 1 — Foundations | C61: trước | D61: before / in front | E61: 前 | F61: cin | G61: Time
A62: 61 | B62: Part 1 — Foundations | C62: sáng | D62: morning | E62: 早晨 | F62: zou-san | G62: Time
A63: 62 | B63: Part 1 — Foundations | C63: chiều | D63: afternoon/evening | E63: 下午 | F63: haa-ng | G63: Time
A64: 63 | B64: Part 1 — Foundations | C64: tối | D64: evening/night | E64: 晚上 | F64: maan-seung | G64: Time
A65: 64 | B65: Part 1 — Foundations | C65: đêm | D65: night | E65: 夜 | F65: je | G65: Time
A66: 65 | B66: Part 1 — Foundations | C66: thứ Hai | D66: Monday | E66: 星期一 | F66: sing-kei-jat | G66: Time
A67: 66 | B67: Part 1 — Foundations | C67: thứ Ba | D67: Tuesday | E67: 星期二 | F67: sing-kei-ji | G67: Time
... A78: 77 | B78: Part 1 — Foundations | C78: khi | D78: when | E78: 當...時 | F78: dong...si | G78: Time
A79: 78 | B79: Part 1 — Foundations | C79: đã | D79: past tense marker | E79: 已 | F79: ji | G79: Time | H79: grammar particle
A80: 79 | B80: Part 1 — Foundations | C80: đang | D80: present continuous marker | E80: 正在 | F80: zing-zoi | G80: Time | H80: grammar particle
A81: 80 | B81: Part 1 — Foundations | C81: sẽ | D81: future marker | E81: 將會 | F81: zoeng-wui | G81: Time | H81: grammar particle
A82: 81 | B82: Part 1 — Foundations | C82: vừa | D82: just (did) | E82: 剛剛 | F82: gong-gong | G82: Time
A83: 82 | B83: Part 1 — Foundations | C83: rồi | D83: already / done | E83: 已經 | F83: ji-ging | G83: Time
A84: 83 | B84: Part 1 — Foundations | C84: chưa | D84: not yet | E84: 未 | F84: mei | G84: Time
A85: 84 | B85: Part 1 — Foundations | C85: xin chào | D85: hello | E85: 你好 | F85: nei-hou | G85: Greetings
A86: 85 | B86: Part 1 — Foundations | C86: tạm biệt | D86: goodbye | E86: 再見 | F86: zoi-gin | G86: Greetings
A87: 86 | B87: Part 1 — Foundations | C87: cảm ơn | D87: thank you | E87: 感謝 | F87: gam-ze | G87: Greetings | H87: Sino-Viet: cảm ơn
A88: 87 | B88: Part 1 — Foundations | C88: xin lỗi | D88: sorry / excuse me | E88: 對不起 | F88: deoi-m-zyu | G88: Greetings
A89: 88 | B89: Part 1 — Foundations | C89: không có gì | D89: you're welcome / no problem | E89: 沒關係 | F89: mut-gwaan-hai | G89: Greetings
A90: 89 | B90: Part 1 — Foundations | C90: vâng / dạ | D90: yes (polite) | E90: 是 | F90: si | G90: Greetings | H90: dạ is Southern
A91: 90 | B91: Part 1 — Foundations | C91: không | D91: no / not | E91: 不/沒 | F91: bat/mut | G91: Greetings
A92: 91 | B92: Part 1 — Foundations | C92: được | D92: okay / can / acceptable | E92: 可以/好 | F92: ho-ji/hou | G92: Greetings
A93: 92 | B93: Part 1 — Foundations | C93: ơi | D93: hey! (calling someone) | E93: 喂 | F93: wai | G93: Greetings
A94: 93 | B94: Part 1 — Foundations | C94: chào mừng | D94: welcome | E94: 歡迎 | F94: fun-jing | G94: Greetings | H94: Sino-Viet: hoan nghênh
A95: 94 | B95: Part 1 — Foundations | C95: khỏe không? | D95: how are you? | E95: 你好嗎? | F95: nei-hou-maa | G95: Greetings
A96: 95 | B96: Part 1 — Foundations | C96: khỏe | D96: healthy / well | E96: 健康 | F96: gin-hong | G96: Greetings
A97: 96 | B97: Part 1 — Foundations | C97: vui | D97: happy | E97: 快樂 | F97: faai-lok | G97: Greetings
A98: 97 | B98: Part 1 — Foundations | C98: buồn | D98: sad | E98: 傷心 | F98: soeng-sam | G98: Greetings
A99: 98 | B99: Part 1 — Foundations | C99: là | D99: to be (identity) | E99: 是 | F99: si | G99: Core Verbs | H99: no conjugation in Viet
A100: 99 | B100: Part 1 — Foundations | C100: có | D100: to have / there is | E100: 有 | F100: jau | G100: Core Verbs
A101: 100 | B101: Part 1 — Foundations | C101: không có | D101: to not have / there isn't | E101: 沒有 | F101: mut-jau | G101: Core Verbs
A102: 101 | B102: Part 1 — Foundations | C102: làm | D102: to do / to make | E102: 做 | F102: zou | G102: Core Verbs
A103: 102 | B103: Part 1 — Foundations | C103: đi | D103: to go | E103: 去 | F103: heoi | G103: Core Verbs
A104: 103 | B104: Part 1 — Foundations | C104: đến | D104: to come / to arrive | E104: 來/到 | F104: lai/dou | G104: Core Verbs
A105: 104 | B105: Part 1 — Foundations | C105: về | D105: to return / about | E105: 回 | F105: wui | G105: Core Verbs
A106: 105 | B106: Part 1 — Foundations | C106: ra | D106: to go out | E106: 出 | F106: ceot | G106: Core Verbs
A107: 106 | B107: Part 1 — Foundations | C107: vào | D107: to enter / in | E107: 進/入 | F107: zeon/jap | G107: Core Verbs
A108: 107 | B108: Part 1 — Foundations | C108: lên | D108: to go up | E108: 上 | F108: soeng | G108: Core Verbs
A109: 108 | B109: Part 1 — Foundations | C109: xuống | D109: to go down | E109: 下 | F109: haa | G109: Core Verbs
A110: 109 | B110: Part 1 — Foundations | C110: ăn | D110: to eat | E110: 食 | F110: sik | G110: Core Verbs
...
